{
	"backtrace" : 2,
	"backtraceGraph" : 
	{
		"commands" : 
		[
			"add_custom_target",
			"add_llvm_library"
		],
		"files" : 
		[
			"cmake/modules/AddLLVM.cmake",
			"lib/DxilDia/CMakeLists.txt"
		],
		"nodes" : 
		[
			{
				"file" : 1
			},
			{
				"command" : 1,
				"file" : 1,
				"line" : 8,
				"parent" : 0
			},
			{
				"command" : 0,
				"file" : 0,
				"line" : 560,
				"parent" : 1
			}
		]
	},
	"dependencies" : 
	[
		{
			"id" : "LLVMDxilDia::@9fae9f067c7ff443dcb9"
		}
	],
	"id" : "install-LLVMDxilDia::@9fae9f067c7ff443dcb9",
	"name" : "install-LLVMDxilDia",
	"paths" : 
	{
		"build" : "lib/DxilDia",
		"source" : "lib/DxilDia"
	},
	"sourceGroups" : 
	[
		{
			"name" : "",
			"sourceIndexes" : 
			[
				0
			]
		},
		{
			"name" : "CMake Rules",
			"sourceIndexes" : 
			[
				1
			]
		}
	],
	"sources" : 
	[
		{
			"backtrace" : 2,
			"isGenerated" : true,
			"path" : "out/build/x64-Debug/lib/DxilDia/CMakeFiles/install-LLVMDxilDia",
			"sourceGroupIndex" : 0
		},
		{
			"backtrace" : 0,
			"isGenerated" : true,
			"path" : "out/build/x64-Debug/lib/DxilDia/CMakeFiles/install-LLVMDxilDia.rule",
			"sourceGroupIndex" : 1
		}
	],
	"type" : "UTILITY"
}
